str_basic_encryption/__init__.py
str_basic_encryption/encryption.py
str_basic_encryption-0.0.1.dist-info/LICENSE
str_basic_encryption-0.0.1.dist-info/METADATA
str_basic_encryption-0.0.1.dist-info/WHEEL
str_basic_encryption-0.0.1.dist-info/top_level.txt
str_basic_encryption-0.0.1.dist-info/RECORD
